{
  "pathName": "实际上传加密文件",
  "path": "/encrypted/upload/file",
  "pathType": "POST",
  "mockType": "mockjsTemplate",
  "queryParams": {},
  "headers": {
    "nas-token": "",
    "Crypto-Token": "",
    "taskID": "",
    "Uploaded-Size": "",
    "Total-Size": "",
    "Content-Length": ""
  },
  "pathContent": {
    "code": 200,
    "message": "success",
    "data": {
      "code": "@integer(1,100000)",
      "data": "@string",
      "message": "@string"
    }
  },
  "bodyParams": null,
  "responseHeaders": {
    "Content-Type": "application/json"
  },
  "fileName": "实际上传加密文件_1750833035548.json",
  "createdAt": "2025-06-25T06:30:35.422Z"
}