{
  "pathName": "实际上传加密文件",
  "path": "/api/v2/encrypted/upload/file",
  "pathType": "POST",
  "mockType": "mockjsTemplate",
  "queryParams": {},
  "headers": {
    "nas-token": "",
    "Crypto-Token": "",
    "taskID": "43ff8897-b70f-479a-92e1-9121fbe51cf9",
    "Uploaded-Size": "",
    "Total-Size": 163490,
    "Content-Length": 163490,
    "Sha1": ""
  },
  "pathContent": {
    "code": 200,
    "message": "success",
    "data": {
      "code": "@integer(1,100000)",
      "data": "@string",
      "message": "@string"
    }
  },
  "bodyParams": null,
  "responseHeaders": {
    "Content-Type": "application/json"
  },
  "fileName": "实际上传加密文件_1750833036329.json",
  "createdAt": "2025-06-25T06:30:35.428Z"
}