{
  "pathName": "获取回收站文件列表",
  "path": "/trash/list",
  "pathType": "POST",
  "mockType": "mockjsTemplate",
  "queryParams": {
    "nas-token": ""
  },
  "queryParamsDesc": {
    "nas-token": {
      "desc": "需要鉴权的API请求令牌(放请求头或者请求参数，二选一)",
      "type": "string"
    }
  },
  "headers": {
    "nas-token": ""
  },
  "responseHeaders": {
    "Content-Type": "application/json"
  },
  "responseHeadersDesc": {
    "nas-token": {
      "desc": "需要鉴权的API请求令牌(放请求头或者请求参数，二选一)",
      "type": "string"
    }
  },
  "pathContent": {
    "code": 200,
    "message": "success",
    "data": {
      "code": "@integer(1,100000)",
      "data": {
        "totalSize": "@integer(1,100000)",
        "trashItems": [
          {
            "deletionDate": "@string",
            "extension": "@string",
            "fileSize": "@integer(1,100000)",
            "isDirectory": "@boolean",
            "originalFileName": "@string",
            "originalFilePath": {
              "filePath": "@string",
              "storageInfo": {
                "partitionLabel": "@string",
                "partitionUUID": "@string",
                "storageType": "@pick([0,1,2,3])",
                "userID": "@string"
              }
            },
            "realFileName": "@string",
            "subDirCount": "@integer(1,100000)",
            "subFileCount": "@integer(1,100000)",
            "updateTime": "@string",
            "uuid": "@string"
          }
        ]
      },
      "message": "@string"
    }
  },
  "pathContentDesc": {
    "type": "object",
    "desc": "",
    "fields": {
      "code": {
        "type": "integer",
        "desc": "状态响应码"
      },
      "data": {
        "type": "object",
        "desc": "响应数据",
        "fields": {
          "totalSize": {
            "type": "integer",
            "desc": "文件总大小"
          },
          "trashItems": {
            "type": "array",
            "desc": "回收站文件列表",
            "items": {
              "type": "object",
              "desc": "",
              "fields": {
                "deletionDate": {
                  "type": "string",
                  "desc": "放入回收站的UTC时间戳"
                },
                "extension": {
                  "type": "string",
                  "desc": "TrashFilePath    linc_fs.FileWithStorage `json:\"trashFilePath\"`    // 存放在回收站的文件完整路径(前端不需要知道回收站文件的具体路径)"
                },
                "fileSize": {
                  "type": "integer",
                  "desc": "垃圾文件大小"
                },
                "isDirectory": {
                  "type": "boolean",
                  "desc": "垃圾文件是否为目录"
                },
                "originalFileName": {
                  "type": "string",
                  "desc": "原始文件名称"
                },
                "originalFilePath": {
                  "type": "object",
                  "desc": "原始文件完整路径",
                  "fields": {
                    "filePath": {
                      "type": "string",
                      "desc": "要操作的相对文件路径"
                    },
                    "storageInfo": {
                      "type": "object",
                      "desc": "存储空间的详细信息",
                      "fields": {
                        "partitionLabel": {
                          "type": "string",
                          "desc": "存储空间名称(作为参数时，不用填写)"
                        },
                        "partitionUUID": {
                          "type": "string",
                          "desc": "盘序号"
                        },
                        "storageType": {
                          "type": "object",
                          "desc": "空间类型, 0-公共空间，1-用户空间,2-加密空间，3-外部空间(包括U盘、外部磁盘)",
                          "fields": {}
                        },
                        "userID": {
                          "type": "string",
                          "desc": "用户名"
                        }
                      }
                    }
                  }
                },
                "realFileName": {
                  "type": "string",
                  "desc": "存放在回收站的文件名称"
                },
                "subDirCount": {
                  "type": "integer",
                  "desc": "子文件目录数量"
                },
                "subFileCount": {
                  "type": "integer",
                  "desc": "子文件数量"
                },
                "updateTime": {
                  "type": "string",
                  "desc": "当前垃圾信息文件的修改UTC时间戳"
                },
                "uuid": {
                  "type": "string",
                  "desc": "文件唯一标识符"
                }
              }
            }
          }
        }
      },
      "message": {
        "type": "string",
        "desc": "响应消息"
      }
    }
  },
  "bodyParams": {
    "partitionLabel": "@string",
    "partitionUUID": "@string",
    "storageType": "@pick([0,1,2,3])",
    "userID": "@string"
  },
  "bodyParamsDesc": {
    "type": "object",
    "desc": "",
    "fields": {
      "partitionLabel": {
        "type": "string",
        "desc": "存储空间名称(作为参数时，不用填写)"
      },
      "partitionUUID": {
        "type": "string",
        "desc": "盘序号"
      },
      "storageType": {
        "type": "object",
        "desc": "空间类型, 0-公共空间，1-用户空间,2-加密空间，3-外部空间(包括U盘、外部磁盘)",
        "fields": {}
      },
      "userID": {
        "type": "string",
        "desc": "用户名"
      }
    }
  },
  "group": "存储空间",
  "fileName": "获取回收站文件列表_1751374644806.json",
  "createdAt": "2025-07-01T12:57:23.828Z"
}