{
  "pathName": "获取缩略图文件路径",
  "path": "/api/v2/storage/path/thumbnail",
  "pathType": "GET",
  "mockType": "mockjsTemplate",
  "queryParams": {
    "nas-token": "",
    "path": ""
  },
  "headers": {
    "nas-token": ""
  },
  "pathContent": {
    "code": 200,
    "message": "success",
    "data": {
      "code": "@integer(1,100000)",
      "data": {
        "path": "@string"
      },
      "message": "@string"
    }
  },
  "bodyParams": null,
  "responseHeaders": {
    "Content-Type": "application/json"
  },
  "fileName": "获取缩略图文件路径_1750833035981.json",
  "createdAt": "2025-06-25T06:30:35.429Z"
}